vine/__init__.py
vine/abstract.py
vine/five.py
vine/funtools.py
vine/promises.py
vine/synchronization.py
vine/utils.py
vine-1.1.2.dist-info/DESCRIPTION.rst
vine-1.1.2.dist-info/METADATA
vine-1.1.2.dist-info/RECORD
vine-1.1.2.dist-info/WHEEL
vine-1.1.2.dist-info/metadata.json
vine-1.1.2.dist-info/top_level.txt
